terracollect/__init__.py
terracollect-0.0.0.dist-info/METADATA
terracollect-0.0.0.dist-info/WHEEL
terracollect-0.0.0.dist-info/top_level.txt
terracollect-0.0.0.dist-info/RECORD
